conectores/__init__.py
conectores/base_emissora.py
conectores-0.0.3.dist-info/METADATA
conectores-0.0.3.dist-info/WHEEL
conectores-0.0.3.dist-info/RECORD
