Metadata-Version: 2.1
Name: conectores
Version: 0.0.3
Summary: Pacote personalizado de conectores OFDC
Author: Isaac da Silva Farias
Author-email: zackfarias.Pc@gmail.com
Requires-Python: >=3.11,<4.0
Classifier: Programming Language :: Python :: 3
Classifier: Programming Language :: Python :: 3.11
Classifier: Programming Language :: Python :: 3.12
